{
  "lastUpdated": "2026-05-07T11:18:52.809580+00:00",
  "totalLeads": 49,
  "totalFound": 0,
  "source": "BatchData",
  "leads": [
    {
      "id": "f5bedc2fe36348cd",
      "county": "clark",
      "type": "pre-foreclosure",
      "owner": "Nestor Mulgado Urgelles",
      "address": "1252 Little Sidnee Dr, Las Vegas NV",
      "amount": null,
      "filingDate": "2026-04-10T00:00:00.000Z",
      "recordingDate": "2026-04-10T00:00:00.000Z",
      "caseNumber": "",
      "phone": null,
      "score": 99,
      "scrapedAt": "2026-05-07T11:18:52.808920+00:00",
      "propertyType": "",
      "bedrooms": null,
      "estimatedValue": 572262,
      "auctionDate": "",
      "lender": "Newrez Llc",
      "notes": "Notice of Default | Trustee: Sables Llc | Est. Value: $572,262",
      "source": "BatchData Pre-Foreclosure"
    },
    {
      "id": "08c2a145a09d8380",
      "county": "clark",
      "type": "pre-foreclosure",
      "owner": "JOSEPH KWIATKOWSKI SEPARATE PROPERTY TRUST; Kwiatkowski",
      "address": "1353 Volturno Way, Henderson NV",
      "amount": null,
      "filingDate": "2026-04-17T00:00:00.000Z",
      "recordingDate": "2026-04-17T00:00:00.000Z",
      "caseNumber": "",
      "phone": null,
      "score": 98,
      "scrapedAt": "2026-05-07T11:18:52.809422+00:00",
      "propertyType": "",
      "bedrooms": null,
      "estimatedValue": 829591,
      "auctionDate": "",
      "lender": "Meridias Capital Inc",
      "notes": "Notice of Default | Trustee: Sables Llc | Est. Value: $829,591",
      "source": "BatchData Pre-Foreclosure"
    },
    {
      "id": "c60fce77546ec41b",
      "county": "clark",
      "type": "pre-foreclosure",
      "owner": "Joseph J Starr",
      "address": "7430 Bisonwood Ave, Las Vegas NV",
      "amount": "$468,920.00",
      "filingDate": "2026-03-31T00:00:00.000Z",
      "recordingDate": "2026-03-31T00:00:00.000Z",
      "caseNumber": "24-00678-NS-NV",
      "phone": null,
      "score": 97,
      "scrapedAt": "2026-05-07T11:18:52.809301+00:00",
      "propertyType": "",
      "bedrooms": null,
      "estimatedValue": 678149,
      "auctionDate": "2026-05-08",
      "lender": "",
      "notes": "Notice of Sale | Auction: 2026-05-08 | @ 930 S 4th Street, Las Vegas | Trustee: National Default Servicing Corporation | Case: 24-00678-NS-NV | Est. Value: $678,149",
      "source": "BatchData Pre-Foreclosure"
    },
    {
      "id": "cd37ebd48592fa0e",
      "county": "clark",
      "type": "pre-foreclosure",
      "owner": "Mary Belle Mccullough; Kerry C Palakanis",
      "address": "2820 Aragon Terrace Way, Henderson NV",
      "amount": null,
      "filingDate": "2026-04-03T00:00:00.000Z",
      "recordingDate": "2026-04-03T00:00:00.000Z",
      "caseNumber": "",
      "phone": null,
      "score": 97,
      "scrapedAt": "2026-05-07T11:18:52.809385+00:00",
      "propertyType": "",
      "bedrooms": null,
      "estimatedValue": 765229,
      "auctionDate": "",
      "lender": "Evergreen Moneysource Mtg Co",
      "notes": "Notice of Default | Trustee: Quality Loan Service Corporation | Est. Value: $765,229",
      "source": "BatchData Pre-Foreclosure"
    },
    {
      "id": "5c6d0b4d3962e1a1",
      "county": "clark",
      "type": "pre-foreclosure",
      "owner": "Gary Lawless",
      "address": "10817 Beringer Dr, Las Vegas NV",
      "amount": null,
      "filingDate": "2026-04-09T00:00:00.000Z",
      "recordingDate": "2026-04-09T00:00:00.000Z",
      "caseNumber": "",
      "phone": null,
      "score": 97,
      "scrapedAt": "2026-05-07T11:18:52.809401+00:00",
      "propertyType": "",
      "bedrooms": null,
      "estimatedValue": 1531453,
      "auctionDate": "",
      "lender": "Vassar Real Estate Llc",
      "notes": "Notice of Default | Trustee: Nevada Trust Deed Services | Est. Value: $1,531,453",
      "source": "BatchData Pre-Foreclosure"
    },
    {
      "id": "8bfea1d69018e671",
      "county": "clark",
      "type": "pre-foreclosure",
      "owner": "ANNETTE ROGERS TRUST; Rogers",
      "address": "6213 Laredo St, Las Vegas NV",
      "amount": null,
      "filingDate": "2026-04-09T00:00:00.000Z",
      "recordingDate": "2026-04-09T00:00:00.000Z",
      "caseNumber": "25-01265NV",
      "phone": null,
      "score": 96,
      "scrapedAt": "2026-05-07T11:18:52.809236+00:00",
      "propertyType": "",
      "bedrooms": null,
      "estimatedValue": 683048,
      "auctionDate": "2026-05-08",
      "lender": "Chaos Home Loans Llc",
      "notes": "Notice of Sale | Auction: 2026-05-08 | @ 930 S Fourth St, Las Vegas | Trustee: Affinia Default Services Llc | Case: 25-01265NV | Est. Value: $683,048",
      "source": "BatchData Pre-Foreclosure"
    },
    {
      "id": "e85638dd4771422c",
      "county": "clark",
      "type": "pre-foreclosure",
      "owner": "Tommy Anderson",
      "address": "305 Petrus Ct, North Las Vegas NV",
      "amount": "$355,618.00",
      "filingDate": "2026-03-31T00:00:00.000Z",
      "recordingDate": "2026-03-31T00:00:00.000Z",
      "caseNumber": "",
      "phone": null,
      "score": 90,
      "scrapedAt": "2026-05-07T11:18:52.809341+00:00",
      "propertyType": "",
      "bedrooms": null,
      "estimatedValue": 603366,
      "auctionDate": "2026-05-21",
      "lender": "Gfl Capital Mortgage Inc",
      "notes": "Notice of Sale | Auction: 2026-05-21 | @ 930 S 4th St, Las Vegas | Trustee: Mtc Financial Inc | Est. Value: $603,366",
      "source": "BatchData Pre-Foreclosure"
    },
    {
      "id": "121bbf671b7d48a7",
      "county": "clark",
      "type": "pre-foreclosure",
      "owner": "Edison L Rojas; Jasmine M Rojas",
      "address": "2169 Rio Rancho Pointe Pl, Henderson NV",
      "amount": null,
      "filingDate": "2026-04-10T00:00:00.000Z",
      "recordingDate": "2026-04-10T00:00:00.000Z",
      "caseNumber": "",
      "phone": null,
      "score": 76,
      "scrapedAt": "2026-05-07T11:18:52.809273+00:00",
      "propertyType": "",
      "bedrooms": null,
      "estimatedValue": 404089,
      "auctionDate": "",
      "lender": "Shannon Investments Llc",
      "notes": "Notice of Default | Trustee: Nestor Solutions Llc | Est. Value: $404,089",
      "source": "BatchData Pre-Foreclosure"
    },
    {
      "id": "7a81b2697770199f",
      "county": "clark",
      "type": "pre-foreclosure",
      "owner": "Anthony R Lewis",
      "address": "5909 Vegas Dr, Las Vegas NV",
      "amount": null,
      "filingDate": "2026-04-08T00:00:00.000Z",
      "recordingDate": "2026-04-08T00:00:00.000Z",
      "caseNumber": "",
      "phone": null,
      "score": 72,
      "scrapedAt": "2026-05-07T11:18:52.809429+00:00",
      "propertyType": "",
      "bedrooms": null,
      "estimatedValue": 233813,
      "auctionDate": "",
      "lender": "Evergreen Moneysource Mtg Co",
      "notes": "Notice of Default | Trustee: Nestor Solutions Llc | Est. Value: $233,813",
      "source": "BatchData Pre-Foreclosure"
    },
    {
      "id": "4c1fc791cc35a55a",
      "county": "clark",
      "type": "pre-foreclosure",
      "owner": "Korey Deron Rideout",
      "address": "2420 Rainy Meadows Ave, North Las Vegas NV",
      "amount": null,
      "filingDate": "2026-03-31T00:00:00.000Z",
      "recordingDate": "2026-03-31T00:00:00.000Z",
      "caseNumber": "",
      "phone": null,
      "score": 71,
      "scrapedAt": "2026-05-07T11:18:52.809360+00:00",
      "propertyType": "",
      "bedrooms": null,
      "estimatedValue": 379451,
      "auctionDate": "2026-05-22",
      "lender": "Nova Financial & Investment Corporation",
      "notes": "Notice of Sale | Auction: 2026-05-22 | Trustee: Mtc Financial Inc | Est. Value: $379,451",
      "source": "BatchData Pre-Foreclosure"
    },
    {
      "id": "b54371035a62440e",
      "county": "clark",
      "type": "pre-foreclosure",
      "owner": "Danielle Olandes",
      "address": "4010 Passing Storm Ln, North Las Vegas NV",
      "amount": "$444,473.00",
      "filingDate": "2026-04-20T00:00:00.000Z",
      "recordingDate": "2026-04-20T00:00:00.000Z",
      "caseNumber": "25-76669",
      "phone": null,
      "score": 56,
      "scrapedAt": "2026-05-07T11:18:52.809440+00:00",
      "propertyType": "",
      "bedrooms": null,
      "estimatedValue": 473948,
      "auctionDate": "2026-06-12",
      "lender": "Lone Mortgage Inc",
      "notes": "Notice of Sale | Auction: 2026-06-12 | @ 930 S 4th St, Las Vegas | Trustee: Sables Llc | Case: 25-76669 | Est. Value: $473,948",
      "source": "BatchData Pre-Foreclosure"
    },
    {
      "id": "0e9ef47ff2a4eee5",
      "county": "clark",
      "type": "pre-foreclosure",
      "owner": "TIMOTHY FORREST LLC",
      "address": "631 Lomprey Ct, Henderson NV",
      "amount": "$874,568.00",
      "filingDate": "2025-07-29T00:00:00.000Z",
      "caseNumber": "",
      "phone": null,
      "score": 50,
      "scrapedAt": "2026-04-20T16:28:44.976445+00:00",
      "propertyType": "",
      "bedrooms": null,
      "estimatedValue": 1459634,
      "auctionDate": "",
      "lender": "Greenbox Loans, Inc.",
      "notes": "Notice of Default | Trustee: Prestige Default Services Llc | Est. Value: $1,459,634",
      "source": "BatchData Pre-Foreclosure"
    },
    {
      "id": "4a7eec64b5416a5e",
      "county": "clark",
      "type": "pre-foreclosure",
      "owner": "Johnathon Brynt Blair; Rebecca Josephine Blair",
      "address": "7516 Via Fiorentino St, Las Vegas NV",
      "amount": "$1,158,542.00",
      "filingDate": "2026-03-10T00:00:00.000Z",
      "caseNumber": "",
      "phone": null,
      "score": 50,
      "scrapedAt": "2026-04-20T16:28:44.976473+00:00",
      "propertyType": "",
      "bedrooms": null,
      "estimatedValue": 1368642,
      "auctionDate": "",
      "lender": "Castle & Cooke Mortgage Llc",
      "notes": "Notice of Default | Trustee: Sables Llc | Est. Value: $1,368,642",
      "source": "BatchData Pre-Foreclosure"
    },
    {
      "id": "136145841caeec0b",
      "county": "clark",
      "type": "pre-foreclosure",
      "owner": "SATICOY BAY LLC",
      "address": "8304 Broad Peak Dr, Las Vegas NV",
      "amount": "$637,500.00",
      "filingDate": "2026-01-20T00:00:00.000Z",
      "caseNumber": "",
      "phone": null,
      "score": 50,
      "scrapedAt": "2026-04-20T16:28:44.976488+00:00",
      "propertyType": "",
      "bedrooms": null,
      "estimatedValue": 880147,
      "auctionDate": "",
      "lender": "Jp Mortgage Group Llc",
      "notes": "Notice of Default | Trustee: Prestige Default Services Llc | Est. Value: $880,147",
      "source": "BatchData Pre-Foreclosure"
    },
    {
      "id": "9c2e3edbb2f621b4",
      "county": "clark",
      "type": "pre-foreclosure",
      "owner": "James Anastasio; Angelika Anastasio",
      "address": "10030 Desert Bighorn Ct, Las Vegas NV",
      "amount": "$486,222.00",
      "filingDate": "2025-10-03T00:00:00.000Z",
      "caseNumber": "",
      "phone": null,
      "score": 50,
      "scrapedAt": "2026-04-20T16:28:44.976734+00:00",
      "propertyType": "",
      "bedrooms": null,
      "estimatedValue": 683810,
      "auctionDate": "2025-11-13",
      "lender": "",
      "notes": "Notice of Default | Auction: 2025-11-13 | @ 930 S 4th St, Las Vegas | Trustee: Rock Financial Services | Est. Value: $683,810",
      "source": "BatchData Pre-Foreclosure"
    },
    {
      "id": "ba91b5989c5bde41",
      "county": "clark",
      "type": "pre-foreclosure",
      "owner": "Jerry Ross; Doris Ross",
      "address": "469 Canyon Dr, Mesquite NV",
      "amount": "$375,978.00",
      "filingDate": "2026-01-28T00:00:00.000Z",
      "caseNumber": "",
      "phone": null,
      "score": 50,
      "scrapedAt": "2026-04-20T16:28:44.976747+00:00",
      "propertyType": "",
      "bedrooms": null,
      "estimatedValue": 347933,
      "auctionDate": "",
      "lender": "Village Capital & Inv Llc",
      "notes": "Notice of Default | Trustee: National Default Servicing Corporation | Est. Value: $347,933",
      "source": "BatchData Pre-Foreclosure"
    },
    {
      "id": "9415dd4d01f35d46",
      "county": "clark",
      "type": "pre-foreclosure",
      "owner": "Saticoy Bay Llc Series 1104 Pi",
      "address": "1104 Pinto Rock Ln Unit 201, Las Vegas NV",
      "amount": null,
      "filingDate": "2026-01-14T00:00:00.000Z",
      "caseNumber": "",
      "phone": null,
      "score": 50,
      "scrapedAt": "2026-04-20T16:28:44.976755+00:00",
      "propertyType": "",
      "bedrooms": null,
      "estimatedValue": 206509,
      "auctionDate": "",
      "lender": "Sun American Mortgage Company",
      "notes": "Notice of Default | Trustee: Clear Recon Corp | Est. Value: $206,509",
      "source": "BatchData Pre-Foreclosure"
    },
    {
      "id": "ae529401c523c15d",
      "county": "clark",
      "type": "pre-foreclosure",
      "owner": "Gonzalez Arturo & Bertha Fam T; GONZALEZ ARTURO P & BERTHA TRS",
      "address": "6617 McCarran St, North Las Vegas NV",
      "amount": "$147,910.00",
      "filingDate": "2026-02-25T00:00:00.000Z",
      "caseNumber": "",
      "phone": null,
      "score": 50,
      "scrapedAt": "2026-04-20T16:28:44.976769+00:00",
      "propertyType": "",
      "bedrooms": null,
      "estimatedValue": 478643,
      "auctionDate": "2026-03-25",
      "lender": "Esplanade Community Association",
      "notes": "Notice of Sale | Auction: 2026-03-25 | Est. Value: $478,643",
      "source": "BatchData Pre-Foreclosure"
    },
    {
      "id": "200793ced25b3419",
      "county": "clark",
      "type": "pre-foreclosure",
      "owner": "Dennis Penate; Alena Penate",
      "address": "1205 High Altitude Ave, North Las Vegas NV",
      "amount": "$324,338.00",
      "filingDate": "2026-02-20T00:00:00.000Z",
      "caseNumber": "",
      "phone": null,
      "score": 50,
      "scrapedAt": "2026-04-20T16:28:44.976777+00:00",
      "propertyType": "",
      "bedrooms": null,
      "estimatedValue": 498833,
      "auctionDate": "",
      "lender": "Everett Financial Inc",
      "notes": "Notice of Default | Trustee: National Default Servicing Corporation | Est. Value: $498,833",
      "source": "BatchData Pre-Foreclosure"
    },
    {
      "id": "c0b5aee8036204a2",
      "county": "clark",
      "type": "pre-foreclosure",
      "owner": "Saticoy Bay Llc Series 1401 Li",
      "address": "1401 Linnbaker Ln Unit 103, Las Vegas NV",
      "amount": "$96,000.00",
      "filingDate": "2026-03-23T00:00:00.000Z",
      "caseNumber": "",
      "phone": null,
      "score": 50,
      "scrapedAt": "2026-04-20T16:28:44.976785+00:00",
      "propertyType": "",
      "bedrooms": null,
      "estimatedValue": 169248,
      "auctionDate": "",
      "lender": "Golden Empire Mortgage Inc",
      "notes": "Notice of Default | Trustee: Quality Loan Service Corporation | Est. Value: $169,248",
      "source": "BatchData Pre-Foreclosure"
    },
    {
      "id": "b11acd9cb71aa991",
      "county": "clark",
      "type": "pre-foreclosure",
      "owner": "Diena Liu",
      "address": "70 Perennial Border Ct, Las Vegas NV",
      "amount": null,
      "filingDate": "2025-09-19T00:00:00.000Z",
      "caseNumber": "",
      "phone": null,
      "score": 50,
      "scrapedAt": "2026-04-20T16:28:44.976796+00:00",
      "propertyType": "",
      "bedrooms": null,
      "estimatedValue": 830734,
      "auctionDate": "2025-10-22",
      "lender": "",
      "notes": "Notice of Default | Auction: 2025-10-22 | @ 930 S 4th St, Las Vegas | Trustee: Rock Financial Services | Est. Value: $830,734",
      "source": "BatchData Pre-Foreclosure"
    },
    {
      "id": "0d937b0751458baa",
      "county": "clark",
      "type": "pre-foreclosure",
      "owner": "William T Jenkins",
      "address": "707 Cottonwood Hill Pl, Henderson NV",
      "amount": "$445,917.00",
      "filingDate": "2025-07-24T00:00:00.000Z",
      "caseNumber": "",
      "phone": null,
      "score": 50,
      "scrapedAt": "2026-04-20T16:28:44.976803+00:00",
      "propertyType": "",
      "bedrooms": null,
      "estimatedValue": 485412,
      "auctionDate": "",
      "lender": "American Financial Network Inc",
      "notes": "Notice of Default | Trustee: Nestor Solutions Llc | Est. Value: $485,412",
      "source": "BatchData Pre-Foreclosure"
    },
    {
      "id": "8c1e056cfe8319a0",
      "county": "clark",
      "type": "pre-foreclosure",
      "owner": "Baden-dewispelaere Erin Kay Tr; EKBD TRUST",
      "address": "3140 Montessouri St, Las Vegas NV",
      "amount": "$829,596.00",
      "filingDate": "2025-12-16T00:00:00.000Z",
      "caseNumber": "",
      "phone": null,
      "score": 50,
      "scrapedAt": "2026-04-20T16:28:44.976812+00:00",
      "propertyType": "",
      "bedrooms": null,
      "estimatedValue": 1667990,
      "auctionDate": "",
      "lender": "Sg Capital Partners Llc",
      "notes": "Notice of Default | Trustee: National Default Servicing Corporation | Est. Value: $1,667,990",
      "source": "BatchData Pre-Foreclosure"
    },
    {
      "id": "d40169f3322b2a9a",
      "county": "clark",
      "type": "pre-foreclosure",
      "owner": "Gary Wisemandle",
      "address": "5650 E Sahara Ave Unit 1012, Las Vegas NV",
      "amount": "$198,438.00",
      "filingDate": "2026-02-24T00:00:00.000Z",
      "caseNumber": "",
      "phone": null,
      "score": 50,
      "scrapedAt": "2026-04-20T16:28:44.976831+00:00",
      "propertyType": "",
      "bedrooms": null,
      "estimatedValue": 173499,
      "auctionDate": "",
      "lender": "Wintrust Mortgage",
      "notes": "Notice of Default | Trustee: Quality Loan Service Corporation | Est. Value: $173,499",
      "source": "BatchData Pre-Foreclosure"
    },
    {
      "id": "0d0f8e20d757e1a0",
      "county": "clark",
      "type": "pre-foreclosure",
      "owner": "Torre Eva Gabrie Dela; Brad A Palubicki",
      "address": "9 Paradise Valley Ct, Henderson NV",
      "amount": "$1,355,102.00",
      "filingDate": "2025-10-03T00:00:00.000Z",
      "caseNumber": "",
      "phone": null,
      "score": 50,
      "scrapedAt": "2026-04-20T16:28:44.976842+00:00",
      "propertyType": "",
      "bedrooms": null,
      "estimatedValue": 3201718,
      "auctionDate": "2025-11-13",
      "lender": "",
      "notes": "Notice of Default | Auction: 2025-11-13 | @ 930 S 4th St, Las Vegas | Trustee: Rock Financial Services | Est. Value: $3,201,718",
      "source": "BatchData Pre-Foreclosure"
    },
    {
      "id": "b7a7090bbbdfb6a0",
      "county": "clark",
      "type": "pre-foreclosure",
      "owner": "Sean V Toly; Sherry Toly",
      "address": "10357 Terra Landings Ave, Las Vegas NV",
      "amount": "$156,140.00",
      "filingDate": "2026-03-24T00:00:00.000Z",
      "caseNumber": "26C009355",
      "phone": null,
      "score": 50,
      "scrapedAt": "2026-04-20T16:28:44.976849+00:00",
      "propertyType": "",
      "bedrooms": null,
      "estimatedValue": 1140008,
      "auctionDate": "",
      "lender": "",
      "notes": "Notice of Lis Pendens | Trustee: Bnd Plastering Inc | Case: 26C009355 | Est. Value: $1,140,008",
      "source": "BatchData Pre-Foreclosure"
    },
    {
      "id": "522b3903bddcaf0e",
      "county": "clark",
      "type": "pre-foreclosure",
      "owner": "Rafael Robert Rhodes; Amber Marie Rhodes",
      "address": "318 Natoire Ct, Henderson NV",
      "amount": "$1,160,204.00",
      "filingDate": "2026-01-23T00:00:00.000Z",
      "caseNumber": "",
      "phone": null,
      "score": 50,
      "scrapedAt": "2026-04-20T16:28:44.976856+00:00",
      "propertyType": "",
      "bedrooms": null,
      "estimatedValue": 1162065,
      "auctionDate": "",
      "lender": "Lennar Mortgage Llc",
      "notes": "Notice of Default | Trustee: National Default Servicing Corporation | Est. Value: $1,162,065",
      "source": "BatchData Pre-Foreclosure"
    },
    {
      "id": "615549f3b14d9b7c",
      "county": "clark",
      "type": "pre-foreclosure",
      "owner": "Monica Y Posada-morales",
      "address": "2572 Favorable Pointe Ct, Henderson NV",
      "amount": "$433,388.00",
      "filingDate": "2026-03-27T00:00:00.000Z",
      "caseNumber": "",
      "phone": null,
      "score": 50,
      "scrapedAt": "2026-04-20T16:28:44.976863+00:00",
      "propertyType": "",
      "bedrooms": null,
      "estimatedValue": 422492,
      "auctionDate": "",
      "lender": "All Western Mortgage Inc",
      "notes": "Notice of Default | Trustee: Quality Loan Service Corporation | Est. Value: $422,492",
      "source": "BatchData Pre-Foreclosure"
    },
    {
      "id": "126e6e1553fcdde2",
      "county": "clark",
      "type": "pre-foreclosure",
      "owner": "HIT HOUSE TOURING INC",
      "address": "61 Garibaldi Way, Henderson NV",
      "amount": null,
      "filingDate": "2025-12-03T00:00:00.000Z",
      "caseNumber": "",
      "phone": null,
      "score": 50,
      "scrapedAt": "2026-04-20T16:28:44.976873+00:00",
      "propertyType": "",
      "bedrooms": null,
      "estimatedValue": 2614912,
      "auctionDate": "2026-01-07",
      "lender": "Slate Fund Llc",
      "notes": "Notice of Sale | Auction: 2026-01-07 | @ 930 S 4th St, Las Vegas | Trustee: Special Default Services Inc | Est. Value: $2,614,912",
      "source": "BatchData Pre-Foreclosure"
    },
    {
      "id": "91807b66af6f41d5",
      "county": "clark",
      "type": "pre-foreclosure",
      "owner": "Arsen Galstyan",
      "address": "9565 Marina Valley Ave, Las Vegas NV",
      "amount": null,
      "filingDate": "2025-12-19T00:00:00.000Z",
      "caseNumber": "",
      "phone": null,
      "score": 50,
      "scrapedAt": "2026-04-20T16:28:44.976880+00:00",
      "propertyType": "",
      "bedrooms": null,
      "estimatedValue": 655251,
      "auctionDate": "",
      "lender": "Azuza Llc",
      "notes": "Notice of Default | Trustee: Prestige Default Services Llc | Est. Value: $655,251",
      "source": "BatchData Pre-Foreclosure"
    },
    {
      "id": "c57f73efa0ea8dd1",
      "county": "clark",
      "type": "pre-foreclosure",
      "owner": "SATICOY BAY LLC",
      "address": "8198 Rock Meadows Dr, Las Vegas NV",
      "amount": null,
      "filingDate": "2026-02-27T00:00:00.000Z",
      "caseNumber": "",
      "phone": null,
      "score": 50,
      "scrapedAt": "2026-04-20T16:28:44.976886+00:00",
      "propertyType": "",
      "bedrooms": null,
      "estimatedValue": 432536,
      "auctionDate": "",
      "lender": "Wells Fargo Bank Na",
      "notes": "Notice of Default | Trustee: Quality Loan Service Corporation | Est. Value: $432,536",
      "source": "BatchData Pre-Foreclosure"
    },
    {
      "id": "9c50addbe227c6f9",
      "county": "clark",
      "type": "pre-foreclosure",
      "owner": "Bradway B Adams; Ann M Adams",
      "address": "175 Strada Fontana, Henderson NV",
      "amount": "$531,980.00",
      "filingDate": "2025-09-29T00:00:00.000Z",
      "caseNumber": "",
      "phone": null,
      "score": 50,
      "scrapedAt": "2026-04-20T16:28:44.976893+00:00",
      "propertyType": "",
      "bedrooms": null,
      "estimatedValue": 546371,
      "auctionDate": "",
      "lender": "Mtg Solutions/colorado Llc",
      "notes": "Notice of Default | Trustee: Affinia Default Services Llc | Est. Value: $546,371",
      "source": "BatchData Pre-Foreclosure"
    },
    {
      "id": "306a614abbdaa377",
      "county": "clark",
      "type": "pre-foreclosure",
      "owner": "Jamie Leigh Collins; Ryan Collins Baker",
      "address": "1218 Highbury Grove St, Henderson NV",
      "amount": "$426,506.00",
      "filingDate": "2026-01-30T00:00:00.000Z",
      "caseNumber": "",
      "phone": null,
      "score": 50,
      "scrapedAt": "2026-04-20T16:28:44.976900+00:00",
      "propertyType": "",
      "bedrooms": null,
      "estimatedValue": 604504,
      "auctionDate": "",
      "lender": "Jpmorgan Chase Bank Na",
      "notes": "Notice of Default | Trustee: Clear Recon Corp | Est. Value: $604,504",
      "source": "BatchData Pre-Foreclosure"
    },
    {
      "id": "d765b25013d4bd76",
      "county": "clark",
      "type": "pre-foreclosure",
      "owner": "Saticoy Bay Llc Series 108 Boy",
      "address": "108 Boysenberry Ln, Henderson NV",
      "amount": null,
      "filingDate": "2026-01-26T00:00:00.000Z",
      "caseNumber": "",
      "phone": null,
      "score": 50,
      "scrapedAt": "2026-04-20T16:28:44.976907+00:00",
      "propertyType": "",
      "bedrooms": null,
      "estimatedValue": 356861,
      "auctionDate": "",
      "lender": "Realteam Mortgage",
      "notes": "Notice of Default | Trustee: National Default Servicing Corporation | Est. Value: $356,861",
      "source": "BatchData Pre-Foreclosure"
    },
    {
      "id": "7d3dea2e22d4168e",
      "county": "clark",
      "type": "pre-foreclosure",
      "owner": "Bay Llc-series Saticoy",
      "address": "3665 Remington Grove Ave, North Las Vegas NV",
      "amount": "$518,630.00",
      "filingDate": "2026-03-31T00:00:00.000Z",
      "caseNumber": "16-00314-NS-NV",
      "phone": null,
      "score": 50,
      "scrapedAt": "2026-04-20T16:28:44.976918+00:00",
      "propertyType": "",
      "bedrooms": null,
      "estimatedValue": 378201,
      "auctionDate": "2026-04-27",
      "lender": "",
      "notes": "Notice of Sale | Auction: 2026-04-27 | @ 930 S 4th Street, Las Vegas | Trustee: National Default Servicing Corporation | Case: 16-00314-NS-NV | Est. Value: $378,201",
      "source": "BatchData Pre-Foreclosure"
    },
    {
      "id": "4ff20c2da32b42d9",
      "county": "clark",
      "type": "pre-foreclosure",
      "owner": "Briana Elizabeth Carroll; Sherry Bragg Baxter",
      "address": "9941 Fletcher Peak Ave, Las Vegas NV",
      "amount": null,
      "filingDate": "2026-04-14T00:00:00.000Z",
      "recordingDate": "2026-04-14T00:00:00.000Z",
      "caseNumber": "",
      "phone": null,
      "score": 49,
      "scrapedAt": "2026-05-07T11:18:52.809448+00:00",
      "propertyType": "",
      "bedrooms": null,
      "estimatedValue": 531955,
      "auctionDate": "",
      "lender": "Jpmorgan Chase Bank Na",
      "notes": "Notice of Default | Trustee: Nevada Trust Deed Services | Est. Value: $531,955",
      "source": "BatchData Pre-Foreclosure"
    },
    {
      "id": "2dcdce60d69df077",
      "county": "clark",
      "type": "pre-foreclosure",
      "owner": "Jeremy Brett Arnold; Jamie Mark Conrad",
      "address": "8908 Crooked Shell Ave, Las Vegas NV",
      "amount": null,
      "filingDate": "2026-04-03T00:00:00.000Z",
      "recordingDate": "2026-04-03T00:00:00.000Z",
      "caseNumber": "",
      "phone": null,
      "score": 45,
      "scrapedAt": "2026-05-07T11:18:52.809477+00:00",
      "propertyType": "",
      "bedrooms": null,
      "estimatedValue": 378391,
      "auctionDate": "",
      "lender": "Freedom Mortgage Corporation",
      "notes": "Notice of Default | Trustee: Nestor Solutions Llc | Est. Value: $378,391",
      "source": "BatchData Pre-Foreclosure"
    },
    {
      "id": "d398fced71c3d36f",
      "county": "clark",
      "type": "pre-foreclosure",
      "owner": "Prescott Jones; Liza Marie Jones",
      "address": "10517 Pacific Palisades Ave, Las Vegas NV",
      "amount": null,
      "filingDate": "2026-04-21T00:00:00.000Z",
      "recordingDate": "2026-04-21T00:00:00.000Z",
      "caseNumber": "",
      "phone": null,
      "score": 38,
      "scrapedAt": "2026-05-07T11:18:52.809368+00:00",
      "propertyType": "",
      "bedrooms": null,
      "estimatedValue": 775017,
      "auctionDate": "",
      "lender": "Guild Mortgage Company Llc",
      "notes": "Notice of Default | Trustee: National Default Servicing Corporation | Est. Value: $775,017",
      "source": "BatchData Pre-Foreclosure"
    },
    {
      "id": "8ae54bcea243478d",
      "county": "clark",
      "type": "pre-foreclosure",
      "owner": "Jon Asdourian",
      "address": "3816 Old Orchard Ct, Las Vegas NV",
      "amount": null,
      "filingDate": "2026-04-16T00:00:00.000Z",
      "recordingDate": "2026-04-16T00:00:00.000Z",
      "caseNumber": "",
      "phone": null,
      "score": 35,
      "scrapedAt": "2026-05-07T11:18:52.809309+00:00",
      "propertyType": "",
      "bedrooms": null,
      "estimatedValue": 597584,
      "auctionDate": "",
      "lender": "Cornerstone First Mortgage Inc",
      "notes": "Notice of Default | Trustee: National Default Servicing Corporation | Est. Value: $597,584",
      "source": "BatchData Pre-Foreclosure"
    },
    {
      "id": "589bcdc0ab39ff7b",
      "county": "clark",
      "type": "pre-foreclosure",
      "owner": "Franklyn R Quintal; Sheree Quintal",
      "address": "3746 Mahalo Cir, Logandale NV",
      "amount": null,
      "filingDate": "2026-04-27T00:00:00.000Z",
      "recordingDate": "2026-04-27T00:00:00.000Z",
      "caseNumber": "",
      "phone": null,
      "score": 30,
      "scrapedAt": "2026-05-07T11:18:52.809350+00:00",
      "propertyType": "",
      "bedrooms": null,
      "estimatedValue": 806807,
      "auctionDate": "",
      "lender": "Castle & Cooke Mortgage Llc",
      "notes": "Notice of Default | Trustee: Prestige Default Services Llc | Est. Value: $806,807",
      "source": "BatchData Pre-Foreclosure"
    },
    {
      "id": "4a24f8028c994b94",
      "county": "clark",
      "type": "pre-foreclosure",
      "owner": "Oscar Luna Garcia",
      "address": "7517 Tinley Creek Ave, Las Vegas NV",
      "amount": null,
      "filingDate": "2026-04-13T00:00:00.000Z",
      "recordingDate": "2026-04-13T00:00:00.000Z",
      "caseNumber": "25-20273-SP-NV",
      "phone": null,
      "score": 29,
      "scrapedAt": "2026-05-07T11:18:52.809330+00:00",
      "propertyType": "",
      "bedrooms": null,
      "estimatedValue": 568080,
      "auctionDate": "2026-05-15",
      "lender": "National Default Servicing Corporation",
      "notes": "Notice of Sale | Auction: 2026-05-15 | @ 930 S Fourth Street, Las Vegas | Trustee: National Default Servicing Corporation | Case: 25-20273-SP-NV | Est. Value: $568,080",
      "source": "BatchData Pre-Foreclosure"
    },
    {
      "id": "4e126f1ed99a81bf",
      "county": "clark",
      "type": "pre-foreclosure",
      "owner": "Michael England; Joslyn England",
      "address": "8255 Las Vegas Blvd S Unit 511, Las Vegas NV",
      "amount": null,
      "filingDate": "2026-04-08T00:00:00.000Z",
      "recordingDate": "2026-04-08T00:00:00.000Z",
      "caseNumber": "",
      "phone": null,
      "score": 27,
      "scrapedAt": "2026-05-07T11:18:52.809318+00:00",
      "propertyType": "",
      "bedrooms": null,
      "estimatedValue": 672796,
      "auctionDate": "",
      "lender": "Mutual Of Omaha Mortgage Inc",
      "notes": "Notice of Default | Trustee: National Default Servicing Corporation | Est. Value: $672,796",
      "source": "BatchData Pre-Foreclosure"
    },
    {
      "id": "17cf12f8dadc6571",
      "county": "clark",
      "type": "pre-foreclosure",
      "owner": "Gregory S Mcpherson",
      "address": "6044 Towboat St Unit 103, North Las Vegas NV",
      "amount": null,
      "filingDate": "2026-04-16T00:00:00.000Z",
      "recordingDate": "2026-04-16T00:00:00.000Z",
      "caseNumber": "",
      "phone": null,
      "score": 27,
      "scrapedAt": "2026-05-07T11:18:52.809470+00:00",
      "propertyType": "",
      "bedrooms": null,
      "estimatedValue": 335420,
      "auctionDate": "",
      "lender": "Loanunited.com Llc",
      "notes": "Notice of Default | Trustee: Sables Llc | Est. Value: $335,420",
      "source": "BatchData Pre-Foreclosure"
    },
    {
      "id": "ba69f01469a52bed",
      "county": "clark",
      "type": "pre-foreclosure",
      "owner": "John Dingman; Kailah Blalark",
      "address": "7139 Calvert Cliffs St, North Las Vegas NV",
      "amount": null,
      "filingDate": "2026-03-31T00:00:00.000Z",
      "recordingDate": "2026-03-31T00:00:00.000Z",
      "caseNumber": "",
      "phone": null,
      "score": 25,
      "scrapedAt": "2026-05-07T11:18:52.809393+00:00",
      "propertyType": "",
      "bedrooms": null,
      "estimatedValue": 535201,
      "auctionDate": "",
      "lender": "Castle & Cooke Mortgage Llc",
      "notes": "Notice of Default | Trustee: Nestor Solutions Llc | Est. Value: $535,201",
      "source": "BatchData Pre-Foreclosure"
    },
    {
      "id": "cbbe163645011c6c",
      "county": "clark",
      "type": "pre-foreclosure",
      "owner": "Michelle P Boxley; Rita F Yeast",
      "address": "236 Callen Falls Ave Unit 1211, Henderson NV",
      "amount": null,
      "filingDate": "2026-04-21T00:00:00.000Z",
      "recordingDate": "2026-04-21T00:00:00.000Z",
      "caseNumber": "",
      "phone": null,
      "score": 19,
      "scrapedAt": "2026-05-07T11:18:52.809282+00:00",
      "propertyType": "",
      "bedrooms": null,
      "estimatedValue": 418290,
      "auctionDate": "",
      "lender": "Lennar Mortgage Llc",
      "notes": "Notice of Default | Trustee: Western Progressive Nevada Inc | Est. Value: $418,290",
      "source": "BatchData Pre-Foreclosure"
    },
    {
      "id": "0cfe9ac7ec200ab1",
      "county": "clark",
      "type": "pre-foreclosure",
      "owner": "Evan R Glusman; Alida E Glusman",
      "address": "9809 Glenrock Dr, Las Vegas NV",
      "amount": null,
      "filingDate": "2026-04-07T00:00:00.000Z",
      "recordingDate": "2026-04-07T00:00:00.000Z",
      "caseNumber": "",
      "phone": null,
      "score": 16,
      "scrapedAt": "2026-05-07T11:18:52.809376+00:00",
      "propertyType": "",
      "bedrooms": null,
      "estimatedValue": 2741100,
      "auctionDate": "",
      "lender": "America First Fcu",
      "notes": "Notice of Default | Trustee: Nevada Trust Deed Services | Est. Value: $2,741,100",
      "source": "BatchData Pre-Foreclosure"
    },
    {
      "id": "f333a9c3a311a64f",
      "county": "clark",
      "type": "pre-foreclosure",
      "owner": "Saticoy Bay Llc Ser 4946 Mozar",
      "address": "4946 Mozart Dr, Las Vegas NV",
      "amount": "$345,737.00",
      "filingDate": "2026-04-09T00:00:00.000Z",
      "recordingDate": "2026-04-09T00:00:00.000Z",
      "caseNumber": "22-30799-BA-NV",
      "phone": null,
      "score": 14,
      "scrapedAt": "2026-05-07T11:18:52.809264+00:00",
      "propertyType": "",
      "bedrooms": null,
      "estimatedValue": 334748,
      "auctionDate": "2026-05-22",
      "lender": "Countrywide Home Loans Inc",
      "notes": "Notice of Sale | Auction: 2026-05-22 | @ 930 S 4th St, Las Vegas | Trustee: National Default Servicing Corporation | Case: 22-30799-BA-NV | Est. Value: $334,748",
      "source": "BatchData Pre-Foreclosure"
    },
    {
      "id": "749209a3ba86d1f5",
      "county": "clark",
      "type": "pre-foreclosure",
      "owner": "Russell Julian Fitzpatrick",
      "address": "2812 Alcoa Ave, Las Vegas NV",
      "amount": "$434,711.00",
      "filingDate": "2026-04-16T00:00:00.000Z",
      "recordingDate": "2026-04-16T00:00:00.000Z",
      "caseNumber": "138119-NV",
      "phone": null,
      "score": 12,
      "scrapedAt": "2026-05-07T11:18:52.809412+00:00",
      "propertyType": "",
      "bedrooms": null,
      "estimatedValue": 446059,
      "auctionDate": "2026-06-26",
      "lender": "Total Quality Financial Inc",
      "notes": "Notice of Sale | Auction: 2026-06-26 | @ 930 S 4th St, Las Vegas | Trustee: Clear Recon Corp | Case: 138119-NV | Est. Value: $446,059",
      "source": "BatchData Pre-Foreclosure"
    },
    {
      "id": "8cff67e03f35830e",
      "county": "clark",
      "type": "pre-foreclosure",
      "owner": "Megan M Moore; Christopher R Moore",
      "address": "4621 Pompano Cir, Las Vegas NV",
      "amount": "$337,490.00",
      "filingDate": "2026-04-14T00:00:00.000Z",
      "recordingDate": "2026-04-14T00:00:00.000Z",
      "caseNumber": "2025-15576-NV",
      "phone": null,
      "score": 3,
      "scrapedAt": "2026-05-07T11:18:52.809461+00:00",
      "propertyType": "",
      "bedrooms": null,
      "estimatedValue": 448945,
      "auctionDate": "2026-05-07",
      "lender": "Freedom Mortgage Corporation",
      "notes": "Notice of Sale | Auction: 2026-05-07 | @ 930 S 4th St, Las Vegas | Trustee: Nestor Solutions Llc | Case: 2025-15576-NV | Est. Value: $448,945",
      "source": "BatchData Pre-Foreclosure"
    }
  ]
}